<?xml version="1.0" encoding="UTF-8" standalone="yes"?>
<!DOCTYPE hofdata
  SYSTEM "hofdata.dtd">
<hofdata>
   <wallitemdata type="ads_mtv_tv2">
      <isanimated/>
      <states>
         <state id="0"/>
         <state id="1"/>
      </states>
   </wallitemdata>
   <productdata>
      <product price="1">
         <code>ads_mtv_tv2</code>
         <name>ads_mtv_tv2 name</name>
         <text>ads_mtv_tv2 desc</text>
         <parameter/>
      </product>
   </productdata>
   <metadata>
      <category name="wall_decoration"/>
   </metadata>
</hofdata>