<?xml version="1.0" encoding="UTF-8" standalone="yes"?>
<!DOCTYPE hofdata
  SYSTEM "hofdata.dtd">
<hofdata>
   <roomitemdata class="ads_dave_cns">
      <dimensions>
         <x>1</x>
         <y>1</y>
         <height>0.0</height>
      </dimensions>
      <sprites>
         <big>2</big>
         <small>2</small>
      </sprites>
      <directions>
         <direction>0</direction>
         <direction>2</direction>
      </directions>
      <notrecyclable/>
      <nottradeable/>
   </roomitemdata>
   <productdata>
      <product price="1">
         <code>DEV ads_dave_cns</code>
         <name>ads_dave_cns</name>
         <text/>
         <parameter/>
      </product>
   </productdata>
   <metadata>
      <category name="other"/>
   </metadata>
</hofdata>