<?xml version="1.0" encoding="ISO-8859-1" ?><!DOCTYPE hofdata SYSTEM "hofdata.dtd"><hofdata>
  <roomitemdata class="clothing_noblecrown" customparams="3488">
    <stacking>
      <stuff/>
    </stacking>
    <dimensions>
      <x>1</x>
      <y>1</y>
      <height>1</height>
    </dimensions>
    <sprites>
      <big>0</big>
      <small>0</small>
    </sprites>
    <directions>
      <direction>0</direction>
      <direction>2</direction>
    </directions>
    <partcolors/>
    <specialtype id="23"/>
    <states>
      <state id="0"/>
      <state id="1"/>
    </states>
  </roomitemdata>
  <productdata>
    <product price="1">
      <code>clothing_noblecrown</code>
      <name>clothing_noblecrown name</name>
      <text>clothing_noblecrown desc</text>
    </product>
  </productdata>
  <metadata>
    <category name="other"/>
  </metadata>
</hofdata>