<?xml version="1.0" encoding="UTF-8"?>
<!DOCTYPE hofdata SYSTEM "hofdata.dtd">
<hofdata>
   <roomitemdata class="hosptl_curtain">
      <dimensions>
         <x>3</x>
         <y>1</y>
         <height>3</height>
      </dimensions>
      <sprites>
         <big>0</big>
         <small>0</small>
      </sprites>
      <directions>
         <direction>0</direction>
         <direction>6</direction>
      </directions>
      <partcolors/>
      <states>
         <state id="0"/>
      </states>
    <builders-club-compatible/>
   </roomitemdata>
   <productdata>
      <product price="1">
         <code>hosptl_curtain</code>
         <name>hosptl_curtain name</name>
         <text>hosptl_curtain desc</text>
         <allowbundlepurchase/>
    </product>
   </productdata>
   <metadata>
      <category name="divider"/>
   </metadata>
</hofdata>
