<?xml version="1.0" encoding="ISO-8859-1" ?><!DOCTYPE hofdata SYSTEM "hofdata.dtd"><hofdata>
  <roomitemdata class="hween14_altarpieces1" runtimeclass="com.sulake.habbo.roomengine.furni.SwitchStateFurni">
    <dimensions>
      <x>1</x>
      <y>1</y>
      <height>0.1</height>
    </dimensions>
    <sprites>
      <big>0</big>
      <small>0</small>
    </sprites>
    <directions>
      <direction>4</direction>
      <direction>2</direction>
    </directions>
    <partcolors/>
    <states>
      <state id="0"/>
      <state id="1"/>
    </states>
    <builders-club-compatible/>
  </roomitemdata>
  <productdata>
    <product price="1">
      <code>hween14_altarpieces1</code>
      <name>hween14_altarpieces1 name</name>
      <text>hween14_altarpieces1 desc</text>
      <allowbundlepurchase/>
    </product>
  </productdata>
  <metadata>
    <category name="other"/>
  </metadata>
</hofdata>