<?xml version="1.0" encoding="ISO-8859-1" ?><!DOCTYPE hofdata SYSTEM "hofdata.dtd"><hofdata>
  <roomitemdata class="pixel_light_blue" runtimeclass="com.sulake.habbo.roomengine.furni.SwitchStateFurni">
    <dimensions>
      <x>1</x>
      <y>1</y>
      <height>1</height>
    </dimensions>
    <sprites>
      <big>0</big>
      <small>0</small>
    </sprites>
    <directions>
      <direction>0</direction>
    </directions>
    <partcolors/>
    <notrecyclable/>
    <nottradeable/>
    <states>
      <state id="0"/>
      <state id="1"/>
    </states>
    <builders-club-compatible/>
  </roomitemdata>
  <productdata>
    <product price="1">
      <code>pixel_light_blue</code>
      <name>pixel_light_blue name</name>
      <text>pixel_light_blue desc</text>
    </product>
  </productdata>
  <metadata>
    <category name="other"/>
  </metadata>
</hofdata>