<?xml version="1.0" encoding="ISO-8859-1" standalone="no"?>
<!DOCTYPE hofdata SYSTEM "hofdata.dtd">
<hofdata>
  <roomitemdata class="plant_rose" runtimeclass="com.sulake.habbo.roomengine.furni.HandItemProviderFurni">
    <dimensions>
      <x>1</x>
      <y>1</y>
      <height>1.0</height>
    </dimensions>
    <sprites>
      <big>1</big>
      <small>1</small>
    </sprites>
    <directions>
      <direction>0</direction>
      <direction>2</direction>
      <direction>4</direction>
      <direction>6</direction>
    </directions>
    <partcolors/>
    <everyone-can-use/>
    <drinks>
      <drink id="1000"/>
    </drinks>
    <builders-club-compatible/>
  </roomitemdata>
  <productdata>
    <product price="3">
      <code>a2 ruusu</code>
      <name>Cut Roses</name>
      <text>Sleek and chic</text>
       <allowbundlepurchase/>
    </product>
  </productdata>
  <metadata>
    <category name="vending_machine"/>
  </metadata>
</hofdata>
