<?xml version="1.0" encoding="ISO-8859-1" ?><!DOCTYPE hofdata SYSTEM "hofdata.dtd"><hofdata>
  <roomitemdata class="theatre_carpet">
    <interaction>
      <stand/>
    </interaction>
    <stacking>
      <items/>      <stuff/>
    </stacking>
    <dimensions>
      <x>1</x>
      <y>1</y>
      <height>0</height>
    </dimensions>
    <sprites>
      <big>1</big>
      <small>1</small>
    </sprites>
    <directions>
      <direction>0</direction>
    </directions>
    <partcolors/>
    <states/>
  </roomitemdata>
  <productdata>
    <product price="1">
      <code>theatre_carpet</code>
      <name>theatre_carpet name</name>
      <text>theatre_carpet desc</text>
    </product>
  </productdata>
  <metadata>
    <category name="other"/>
  </metadata>
</hofdata>