<?xml version="1.0" encoding="ISO-8859-1" ?>
<!DOCTYPE hofdata SYSTEM "hofdata.dtd">
<hofdata>
  <roomitemdata class="wildwest_cabinet" runtimeclass="com.sulake.habbo.roomengine.furni.HandItemProviderFurni">
    <dimensions>
      <x>3</x>
      <y>1</y>
      <height>1</height>
    </dimensions>
    <sprites>
      <big>0</big>
      <small>0</small>
    </sprites>
    <directions>
      <direction>4</direction>
      <direction>2</direction>
    </directions>
    <partcolors/>
    <everyone-can-use/>
    <drinks>
      <drink id="88"/>
    </drinks>
    <builders-club-compatible/>
  </roomitemdata>
  <productdata>
    <product price="1">
      <code>wildwest_cabinet</code>
      <name>wildwest_cabinet name</name>
      <text>wildwest_cabinet desc</text>
         <excludedfromdynamic/>
    </product>
  </productdata>
  <metadata>
    <category name="other"/>
  </metadata>
</hofdata>
