<?xml version="1.0" encoding="UTF-8"?>
<!DOCTYPE hofdata SYSTEM "hofdata.dtd">
<hofdata>
   <wallitemdata type="year2011">
      <isanimated/>
      <states>
         <state id="0"/>
         <state id="1"/>
      </states>
   </wallitemdata>
   <productdata>
      <product price="1">
         <code>year2011</code>
         <name>year2011 name</name>
         <text>year2011 desc</text>
         <allowbundlepurchase/>
    </product>
   </productdata>
   <metadata>
      <category name="wall_decoration"/>
   </metadata>
</hofdata>
