{
  "m_GameObject": {
    "m_FileID": 0,
    "m_PathID": 0
  },
  "m_Enabled": 1,
  "m_Script": {
    "m_FileID": 0,
    "m_PathID": -5115663347374922130
  },
  "m_Name": "trousers_U_apronskirt",
  "xmlAsset": {
    "avatarPartAsset": {
      "name": "trousers_U_apronskirt",
      "parts": [
        {
          "name": "h_lay_lg_4555_2_0",
          "mimeType": "image/png",
          "param": {
            "key": "offset",
            "value": "-18,14"
          }
        },
        {
          "name": "h_lay_lg_4556_2_0",
          "mimeType": "image/png",
          "param": {
            "key": "offset",
            "value": "-21,14"
          }
        },
        {
          "name": "h_lay_lg_4557_2_0",
          "mimeType": "image/png",
          "param": {
            "key": "offset",
            "value": "-27,12"
          }
        },
        {
          "name": "h_std_lg_4555_7_0",
          "mimeType": "image/png",
          "param": {
            "key": "offset",
            "value": "-18,23"
          }
        },
        {
          "name": "h_std_lg_4555_3_0",
          "mimeType": "image/png",
          "param": {
            "key": "offset",
            "value": "-18,24"
          }
        },
        {
          "name": "h_std_lg_4555_2_0",
          "mimeType": "image/png",
          "param": {
            "key": "offset",
            "value": "-17,25"
          }
        },
        {
          "name": "h_std_lg_4555_1_0",
          "mimeType": "image/png",
          "param": {
            "key": "offset",
            "value": "-18,24"
          }
        },
        {
          "name": "h_std_lg_4555_0_0",
          "mimeType": "image/png",
          "param": {
            "key": "offset",
            "value": "-14,26"
          }
        },
        {
          "name": "h_std_lg_4556_3_0",
          "mimeType": "image/png",
          "param": {
            "key": "offset",
            "value": "-23,23"
          }
        },
        {
          "name": "h_std_lg_4556_2_0",
          "mimeType": "image/png",
          "param": {
            "key": "offset",
            "value": "-28,26"
          }
        },
        {
          "name": "h_std_lg_4556_1_0",
          "mimeType": "image/png",
          "param": {
            "key": "offset",
            "value": "-35,24"
          }
        },
        {
          "name": "h_std_lg_4557_3_0",
          "mimeType": "image/png",
          "param": {
            "key": "offset",
            "value": "-25,16"
          }
        },
        {
          "name": "h_std_lg_4557_2_0",
          "mimeType": "image/png",
          "param": {
            "key": "offset",
            "value": "-32,18"
          }
        },
        {
          "name": "h_std_lg_4557_1_0",
          "mimeType": "image/png",
          "param": {
            "key": "offset",
            "value": "-40,16"
          }
        },
        {
          "name": "h_sit_lg_4555_2_0",
          "mimeType": "image/png",
          "param": {
            "key": "offset",
            "value": "-22,26"
          }
        },
        {
          "name": "h_sit_lg_4555_0_0",
          "mimeType": "image/png",
          "param": {
            "key": "offset",
            "value": "-20,35"
          }
        },
        {
          "name": "h_sit_lg_4556_2_0",
          "mimeType": "image/png",
          "param": {
            "key": "offset",
            "value": "-30,25"
          }
        },
        {
          "name": "h_sit_lg_4556_0_0",
          "mimeType": "image/png",
          "param": {
            "key": "offset",
            "value": "-41,31"
          }
        },
        {
          "name": "h_sit_lg_4557_2_0",
          "mimeType": "image/png",
          "param": {
            "key": "offset",
            "value": "-36,23"
          }
        },
        {
          "name": "h_sit_lg_4557_0_0",
          "mimeType": "image/png",
          "param": {
            "key": "offset",
            "value": "-43,30"
          }
        },
        {
          "name": "h_wlk_lg_4555_7_0",
          "mimeType": "image/png",
          "param": {
            "key": "offset",
            "value": "-18,23"
          }
        },
        {
          "name": "h_wlk_lg_4555_7_1",
          "mimeType": "image/png",
          "param": {
            "key": "offset",
            "value": "-18,23"
          }
        },
        {
          "name": "h_wlk_lg_4555_7_2",
          "mimeType": "image/png",
          "param": {
            "key": "offset",
            "value": "-18,23"
          }
        },
        {
          "name": "h_wlk_lg_4555_7_3",
          "mimeType": "image/png",
          "param": {
            "key": "offset",
            "value": "-18,23"
          }
        },
        {
          "name": "h_wlk_lg_4555_3_0",
          "mimeType": "image/png",
          "param": {
            "key": "offset",
            "value": "-18,24"
          }
        },
        {
          "name": "h_wlk_lg_4555_3_1",
          "mimeType": "image/png",
          "param": {
            "key": "offset",
            "value": "-18,24"
          }
        },
        {
          "name": "h_wlk_lg_4555_3_2",
          "mimeType": "image/png",
          "param": {
            "key": "offset",
            "value": "-18,24"
          }
        },
        {
          "name": "h_wlk_lg_4555_3_3",
          "mimeType": "image/png",
          "param": {
            "key": "offset",
            "value": "-18,24"
          }
        },
        {
          "name": "h_wlk_lg_4555_2_0",
          "mimeType": "image/png",
          "param": {
            "key": "offset",
            "value": "-17,25"
          }
        },
        {
          "name": "h_wlk_lg_4555_2_1",
          "mimeType": "image/png",
          "param": {
            "key": "offset",
            "value": "-17,25"
          }
        },
        {
          "name": "h_wlk_lg_4555_2_2",
          "mimeType": "image/png",
          "param": {
            "key": "offset",
            "value": "-17,25"
          }
        },
        {
          "name": "h_wlk_lg_4555_2_3",
          "mimeType": "image/png",
          "param": {
            "key": "offset",
            "value": "-17,25"
          }
        },
        {
          "name": "h_wlk_lg_4555_1_0",
          "mimeType": "image/png",
          "param": {
            "key": "offset",
            "value": "-18,24"
          }
        },
        {
          "name": "h_wlk_lg_4555_1_1",
          "mimeType": "image/png",
          "param": {
            "key": "offset",
            "value": "-18,24"
          }
        },
        {
          "name": "h_wlk_lg_4555_1_2",
          "mimeType": "image/png",
          "param": {
            "key": "offset",
            "value": "-18,24"
          }
        },
        {
          "name": "h_wlk_lg_4555_1_3",
          "mimeType": "image/png",
          "param": {
            "key": "offset",
            "value": "-18,24"
          }
        },
        {
          "name": "h_wlk_lg_4555_0_0",
          "mimeType": "image/png",
          "param": {
            "key": "offset",
            "value": "-14,26"
          }
        },
        {
          "name": "h_wlk_lg_4555_0_1",
          "mimeType": "image/png",
          "param": {
            "key": "offset",
            "value": "-14,26"
          }
        },
        {
          "name": "h_wlk_lg_4555_0_2",
          "mimeType": "image/png",
          "param": {
            "key": "offset",
            "value": "-14,26"
          }
        },
        {
          "name": "h_wlk_lg_4555_0_3",
          "mimeType": "image/png",
          "param": {
            "key": "offset",
            "value": "-14,26"
          }
        },
        {
          "name": "h_wlk_lg_4556_3_0",
          "mimeType": "image/png",
          "param": {
            "key": "offset",
            "value": "-23,23"
          }
        },
        {
          "name": "h_wlk_lg_4556_3_1",
          "mimeType": "image/png",
          "param": {
            "key": "offset",
            "value": "-23,23"
          }
        },
        {
          "name": "h_wlk_lg_4556_3_2",
          "mimeType": "image/png",
          "param": {
            "key": "offset",
            "value": "-23,23"
          }
        },
        {
          "name": "h_wlk_lg_4556_3_3",
          "mimeType": "image/png",
          "param": {
            "key": "offset",
            "value": "-23,23"
          }
        },
        {
          "name": "h_wlk_lg_4556_2_0",
          "mimeType": "image/png",
          "param": {
            "key": "offset",
            "value": "-28,26"
          }
        },
        {
          "name": "h_wlk_lg_4556_2_1",
          "mimeType": "image/png",
          "param": {
            "key": "offset",
            "value": "-28,26"
          }
        },
        {
          "name": "h_wlk_lg_4556_2_2",
          "mimeType": "image/png",
          "param": {
            "key": "offset",
            "value": "-28,26"
          }
        },
        {
          "name": "h_wlk_lg_4556_2_3",
          "mimeType": "image/png",
          "param": {
            "key": "offset",
            "value": "-28,26"
          }
        },
        {
          "name": "h_wlk_lg_4556_1_0",
          "mimeType": "image/png",
          "param": {
            "key": "offset",
            "value": "-35,24"
          }
        },
        {
          "name": "h_wlk_lg_4556_1_1",
          "mimeType": "image/png",
          "param": {
            "key": "offset",
            "value": "-35,24"
          }
        },
        {
          "name": "h_wlk_lg_4556_1_2",
          "mimeType": "image/png",
          "param": {
            "key": "offset",
            "value": "-35,24"
          }
        },
        {
          "name": "h_wlk_lg_4556_1_3",
          "mimeType": "image/png",
          "param": {
            "key": "offset",
            "value": "-35,24"
          }
        },
        {
          "name": "h_wlk_lg_4557_3_0",
          "mimeType": "image/png",
          "param": {
            "key": "offset",
            "value": "-25,16"
          }
        },
        {
          "name": "h_wlk_lg_4557_3_1",
          "mimeType": "image/png",
          "param": {
            "key": "offset",
            "value": "-25,17"
          }
        },
        {
          "name": "h_wlk_lg_4557_3_2",
          "mimeType": "image/png",
          "param": {
            "key": "offset",
            "value": "-25,16"
          }
        },
        {
          "name": "h_wlk_lg_4557_3_3",
          "mimeType": "image/png",
          "param": {
            "key": "offset",
            "value": "-25,17"
          }
        },
        {
          "name": "h_wlk_lg_4557_2_0",
          "mimeType": "image/png",
          "param": {
            "key": "offset",
            "value": "-32,18"
          }
        },
        {
          "name": "h_wlk_lg_4557_2_1",
          "mimeType": "image/png",
          "param": {
            "key": "offset",
            "value": "-32,19"
          }
        },
        {
          "name": "h_wlk_lg_4557_2_2",
          "mimeType": "image/png",
          "param": {
            "key": "offset",
            "value": "-32,18"
          }
        },
        {
          "name": "h_wlk_lg_4557_2_3",
          "mimeType": "image/png",
          "param": {
            "key": "offset",
            "value": "-32,19"
          }
        },
        {
          "name": "h_wlk_lg_4557_1_0",
          "mimeType": "image/png",
          "param": {
            "key": "offset",
            "value": "-40,16"
          }
        },
        {
          "name": "h_wlk_lg_4557_1_1",
          "mimeType": "image/png",
          "param": {
            "key": "offset",
            "value": "-40,17"
          }
        },
        {
          "name": "h_wlk_lg_4557_1_2",
          "mimeType": "image/png",
          "param": {
            "key": "offset",
            "value": "-40,16"
          }
        },
        {
          "name": "h_wlk_lg_4557_1_3",
          "mimeType": "image/png",
          "param": {
            "key": "offset",
            "value": "-40,17"
          }
        }
      ],
      "assetAliases": []
    }
  },
  "effectXmlData": {
    "name": "",
    "description": "",
    "resetOnToggle": 0,
    "sprites": [],
    "avatar": {
      "foregroundString": "",
      "backgroundString": "",
      "ink": 0
    },
    "directions": [],
    "removes": [],
    "adds": [],
    "overrides": [],
    "frames": []
  }
}